smriprep/__about__.py
smriprep/__init__.py
smriprep/__main__.py
smriprep/_version.py
smriprep/conftest.py
smriprep/cli/__init__.py
smriprep/cli/run.py
smriprep/cli/tests/__init__.py
smriprep/cli/tests/test_cli.py
smriprep/conf/__init__.py
smriprep/data/__init__.py
smriprep/data/boilerplate.bib
smriprep/data/io_spec.json
smriprep/data/itkIdentityTransform.txt
smriprep/data/reports-spec.yml
smriprep/data/atlases/L.atlasroi.32k_fs_LR.shape.gii
smriprep/data/atlases/L.atlasroi.59k_fs_LR.shape.gii
smriprep/data/atlases/L.refsulc.164k_fs_LR.shape.gii
smriprep/data/atlases/R.atlasroi.32k_fs_LR.shape.gii
smriprep/data/atlases/R.atlasroi.59k_fs_LR.shape.gii
smriprep/data/atlases/R.refsulc.164k_fs_LR.shape.gii
smriprep/data/atlases/fsaverage.L_LR.spherical_std.164k_fs_LR.surf.gii
smriprep/data/atlases/fsaverage.R_LR.spherical_std.164k_fs_LR.surf.gii
smriprep/data/atlases/fs_L/fs_L-to-fs_LR_fsaverage.L_LR.spherical_std.164k_fs_L.surf.gii
smriprep/data/atlases/fs_L/fsaverage.L.sphere.164k_fs_L.surf.gii
smriprep/data/atlases/fs_R/fs_R-to-fs_LR_fsaverage.R_LR.spherical_std.164k_fs_R.surf.gii
smriprep/data/atlases/fs_R/fsaverage.R.sphere.164k_fs_R.surf.gii
smriprep/data/msm/MSMSulcStrainFinalconf
smriprep/data/msm/MSMSulcStrainSloppyconf
smriprep/data/tests/dataset_description.json
smriprep/interfaces/__init__.py
smriprep/interfaces/cifti.py
smriprep/interfaces/conftest.py
smriprep/interfaces/freesurfer.py
smriprep/interfaces/fsl.py
smriprep/interfaces/gifti.py
smriprep/interfaces/msm.py
smriprep/interfaces/reports.py
smriprep/interfaces/surf.py
smriprep/interfaces/templateflow.py
smriprep/interfaces/workbench.py
smriprep/interfaces/tests/__init__.py
smriprep/interfaces/tests/test_surf.py
smriprep/interfaces/tests/data/__init__.py
smriprep/interfaces/tests/data/lh.sphere.reg.surf.gii
smriprep/interfaces/tests/data/lh.white
smriprep/interfaces/tests/data/sub-01_desc-warped_T1w.nii.gz
smriprep/interfaces/tests/data/sub-01_hemi-L_midthickness.surf.gii
smriprep-0.19.2.dist-info/METADATA
smriprep-0.19.2.dist-info/WHEEL
smriprep-0.19.2.dist-info/entry_points.txt
smriprep-0.19.2.dist-info/licenses/LICENSE
smriprep-0.19.2.dist-info/licenses/NOTICE
smriprep-0.19.2.dist-info/RECORD
