Metadata-Version: 2.4
Name: smriprep
Version: 0.19.2
Summary: Structural MRI Preprocessing Pipelines
Project-URL: Homepage, https://github.com/nipreps/smriprep
Project-URL: Documentation, https://nipreps.org/smriprep
Project-URL: Docker Images, https://hub.docker.com/r/nipreps/smriprep/tags/
Project-URL: NiPreps, https://www.nipreps.org/
Author-email: The NiPreps Developers <nipreps@gmail.com>
License: 
License-File: LICENSE
License-File: NOTICE
Classifier: Development Status :: 5 - Production/Stable
Classifier: Intended Audience :: Science/Research
Classifier: License :: OSI Approved :: Apache Software License
Classifier: Programming Language :: Python :: 3.10
Classifier: Programming Language :: Python :: 3.11
Classifier: Programming Language :: Python :: 3.12
Classifier: Programming Language :: Python :: 3.13
Classifier: Topic :: Scientific/Engineering :: Image Recognition
Requires-Python: >=3.10
Requires-Dist: acres>=0.2
Requires-Dist: indexed-gzip>=1.7
Requires-Dist: lockfile>=0.12.2
Requires-Dist: looseversion>=1.3.0
Requires-Dist: matplotlib>=3.5
Requires-Dist: nibabel>=4.0.1
Requires-Dist: nipype>=1.8.5
Requires-Dist: nireports>=25.3.0
Requires-Dist: nitransforms>=24.1.1
Requires-Dist: niworkflows>=1.14.0
Requires-Dist: numpy>=1.24
Requires-Dist: packaging>=24
Requires-Dist: pybids>=0.16
Requires-Dist: pyyaml>=6.0
Requires-Dist: templateflow>=25.0
Provides-Extra: all
Requires-Dist: coverage[toml]>=5.2.1; extra == 'all'
Requires-Dist: datalad; extra == 'all'
Requires-Dist: duecredit; extra == 'all'
Requires-Dist: nbsphinx; extra == 'all'
Requires-Dist: packaging; extra == 'all'
Requires-Dist: pydot; extra == 'all'
Requires-Dist: pytest-cov>=2.11; extra == 'all'
Requires-Dist: pytest-env; extra == 'all'
Requires-Dist: pytest-xdist>=2.5; extra == 'all'
Requires-Dist: pytest>=8.1; extra == 'all'
Requires-Dist: sphinx; extra == 'all'
Requires-Dist: sphinx-argparse; extra == 'all'
Requires-Dist: sphinx-rtd-theme; extra == 'all'
Requires-Dist: sphinxcontrib-apidoc~=0.3.0; extra == 'all'
Requires-Dist: sphinxcontrib-napoleon; extra == 'all'
Requires-Dist: sphinxcontrib-versioning; extra == 'all'
Provides-Extra: datalad
Requires-Dist: datalad; extra == 'datalad'
Provides-Extra: doc
Requires-Dist: nbsphinx; extra == 'doc'
Requires-Dist: packaging; extra == 'doc'
Requires-Dist: pydot; extra == 'doc'
Requires-Dist: sphinx; extra == 'doc'
Requires-Dist: sphinx-argparse; extra == 'doc'
Requires-Dist: sphinx-rtd-theme; extra == 'doc'
Requires-Dist: sphinxcontrib-apidoc~=0.3.0; extra == 'doc'
Requires-Dist: sphinxcontrib-napoleon; extra == 'doc'
Requires-Dist: sphinxcontrib-versioning; extra == 'doc'
Provides-Extra: docs
Requires-Dist: nbsphinx; extra == 'docs'
Requires-Dist: packaging; extra == 'docs'
Requires-Dist: pydot; extra == 'docs'
Requires-Dist: sphinx; extra == 'docs'
Requires-Dist: sphinx-argparse; extra == 'docs'
Requires-Dist: sphinx-rtd-theme; extra == 'docs'
Requires-Dist: sphinxcontrib-apidoc~=0.3.0; extra == 'docs'
Requires-Dist: sphinxcontrib-napoleon; extra == 'docs'
Requires-Dist: sphinxcontrib-versioning; extra == 'docs'
Provides-Extra: duecredit
Requires-Dist: duecredit; extra == 'duecredit'
Provides-Extra: style
Requires-Dist: flake8; extra == 'style'
Provides-Extra: test
Requires-Dist: coverage[toml]>=5.2.1; extra == 'test'
Requires-Dist: pytest-cov>=2.11; extra == 'test'
Requires-Dist: pytest-env; extra == 'test'
Requires-Dist: pytest-xdist>=2.5; extra == 'test'
Requires-Dist: pytest>=8.1; extra == 'test'
Provides-Extra: tests
Requires-Dist: coverage[toml]>=5.2.1; extra == 'tests'
Requires-Dist: pytest-cov>=2.11; extra == 'tests'
Requires-Dist: pytest-env; extra == 'tests'
Requires-Dist: pytest-xdist>=2.5; extra == 'tests'
Requires-Dist: pytest>=8.1; extra == 'tests'
